cloudmesh/cmd5/CloudmeshPlugin.py
cloudmesh/cmd5/__init__.py
cloudmesh/debug/__init__.py
cloudmesh/debug/command/__init__.py
cloudmesh/debug/command/debug.py
cloudmesh/default/__init__.py
cloudmesh/default/command/__init__.py
cloudmesh/default/command/default.py
cloudmesh/dryrun/__init__.py
cloudmesh/dryrun/command/__init__.py
cloudmesh/dryrun/command/dryrun.py
cloudmesh/man/__init__.py
cloudmesh/man/command/__init__.py
cloudmesh/man/command/man.py
cloudmesh/set/__init__.py
cloudmesh/set/command/__init__.py
cloudmesh/set/command/set.py
cloudmesh/shell/__init__.py
cloudmesh/shell/command.py
cloudmesh/shell/plugin.py
cloudmesh/shell/shell.py
cloudmesh/sysinfo/__init__.py
cloudmesh/sysinfo/command/__init__.py
cloudmesh/sysinfo/command/sysinfo.py
cloudmesh/terminal/__init__.py
cloudmesh/terminal/command/__init__.py
cloudmesh/terminal/command/terminal.py
cloudmesh/var/__init__.py
cloudmesh/var/command/__init__.py
cloudmesh/var/command/var.py
cloudmesh_cmd5-5.0.20.dist-info/LICENSE
cloudmesh_cmd5-5.0.20.dist-info/METADATA
cloudmesh_cmd5-5.0.20.dist-info/WHEEL
cloudmesh_cmd5-5.0.20.dist-info/entry_points.txt
cloudmesh_cmd5-5.0.20.dist-info/top_level.txt
cloudmesh_cmd5-5.0.20.dist-info/RECORD
